autoqt6.py
autoqt6-0.0.8.dist-info/LICENSE
autoqt6-0.0.8.dist-info/METADATA
autoqt6-0.0.8.dist-info/WHEEL
autoqt6-0.0.8.dist-info/top_level.txt
autoqt6-0.0.8.dist-info/RECORD
