Metadata-Version: 2.1
Name: autoqt6
Version: 0.0.8
Summary: Simplify pyqtProperty creation.
Home-page: https://github.com/jrj99/autoqt6/
Author: NaKyle Wright, Jared Jones
Author-email: jared.randall.jones@gmail.com
License: UNKNOWN
Keywords: PyQt,PyQt6,pyqtProperty,PySide6
Platform: UNKNOWN
Classifier: Development Status :: 3 - Alpha
Classifier: Intended Audience :: Developers
Classifier: Operating System :: OS Independent
Classifier: Programming Language :: Python :: 3
Classifier: License :: OSI Approved :: MIT License
Classifier: Topic :: Software Development
Requires-Python: >=3.6
License-File: LICENSE
